geog0111/Chapter3_6.py
geog0111/Chapter3_6A_prerequisites.py
geog0111/__init__.py
geog0111/conf.py
geog0111/course_data.py
geog0111/create_blank_file.py
geog0111/cylog.py
geog0111/d.py
geog0111/data_mask.py
geog0111/database.py
geog0111/demofilt1.py
geog0111/demofilt2.py
geog0111/demofilt3.py
geog0111/demofilt4.py
geog0111/demofilt5.py
geog0111/discharge.py
geog0111/download_lai.py
geog0111/edit_notebook.py
geog0111/expand.py
geog0111/fdict.py
geog0111/filter_movies.py
geog0111/fire_practical_model.py
geog0111/fire_practical_satellite.py
geog0111/fire_practical_telecon.py
geog0111/flatten.py
geog0111/geog_data.py
geog0111/getNOAA.py
geog0111/get_burn.py
geog0111/get_doy.py
geog0111/get_lai.py
geog0111/get_lai2.py
geog0111/get_lai_data.py
geog0111/get_landcover.py
geog0111/get_lc.py
geog0111/get_modis_files.py
geog0111/get_url.py
geog0111/get_weight.py
geog0111/gurlpath.py
geog0111/helloWorld.py
geog0111/howmany.py
geog0111/im_display.py
geog0111/info.py
geog0111/link.py
geog0111/list_of_doys.py
geog0111/lists.py
geog0111/lut_RMSE.py
geog0111/lut_solver.py
geog0111/match_netcdf_to_data.py
geog0111/mkdocs_prep.py
geog0111/model.py
geog0111/modis.py
geog0111/modis_annual.py
geog0111/modis_tiles.py
geog0111/monthdays.py
geog0111/move.py
geog0111/nasa_requests.py
geog0111/nsat.py
geog0111/part1.py
geog0111/plot_landcover.py
geog0111/plot_lc.py
geog0111/process_timeseries.py
geog0111/pull_ba.py
geog0111/pull_lai.py
geog0111/pull_lc.py
geog0111/raster_mask.py
geog0111/regularise.py
geog0111/save_data.py
geog0111/stitch_me.py
geog0111/sys_init.py
geog0111/test.py
geog0111/tester.py
geog0111/tester2.py
geog0111/today.py
geog0111/visfig.py
geog0111-1.1.0.dist-info/AUTHORS
geog0111-1.1.0.dist-info/LICENSE
geog0111-1.1.0.dist-info/METADATA
geog0111-1.1.0.dist-info/WHEEL
geog0111-1.1.0.dist-info/top_level.txt
geog0111-1.1.0.dist-info/RECORD
