Metadata-Version: 2.1
Name: geog0111
Version: 1.1.0
Summary: UCL Geography MSc notes
Home-page: https://github.com/UCL-EO/geog0111
Author: P. Lewis and J. Gomez-Dans
Author-email: p.lewis@ucl.ac.uk
License: MIT
Keywords: scientific computing
Platform: UNKNOWN
Classifier: Programming Language :: Python :: 3
Classifier: License :: OSI Approved :: MIT License
Classifier: Operating System :: OS Independent
Requires-Python: >=3.6
License-File: LICENSE
License-File: AUTHORS
